correlationHistogramAnalysis/__init__.py
correlationHistogramAnalysis/correlation_histogram.py
correlationHistogramAnalysis/dissociation_tracks.py
correlationhistogramanalysis-0.3.0.dist-info/LICENSE
correlationhistogramanalysis-0.3.0.dist-info/METADATA
correlationhistogramanalysis-0.3.0.dist-info/WHEEL
correlationhistogramanalysis-0.3.0.dist-info/RECORD
