Metadata-Version: 2.1
Name: correlationHistogramAnalysis
Version: 0.3.0
Summary: "For in depth analysis of correlation histograms in APT"
License: APACHE 2.0
Author: Shyam Katnagallu
Author-email: s.katnagallu@mpie.de
Requires-Python: >=3.12,<4.0
Classifier: License :: Other/Proprietary License
Classifier: Programming Language :: Python :: 3
Classifier: Programming Language :: Python :: 3.12
Requires-Dist: ifes-apt-tc-data-modeling (>=0.2,<0.3)
Requires-Dist: numpy (>=1.26.4,<2.0.0)
Requires-Dist: pandas (>=2.2.1,<3.0.0)
